MANIFEST.in
README.txt
plonetheme.broadcaster-configure.zcml
setup.cfg
setup.py
Broadcaster/index.html
Broadcaster/images/body-bg.png
Broadcaster/images/code.png
Broadcaster/images/ff.jpg
Broadcaster/images/logo.png
Broadcaster/images/nav-bg.png
Broadcaster/images/post-title.png
Broadcaster/images/quote.png
Broadcaster/images/searchbg.gif
Broadcaster/images/shade.gif
Broadcaster/images/sidebar-title.png
Broadcaster/images/style.css
docs/HISTORY.txt
docs/INSTALL.txt
docs/LICENSE.GPL
docs/LICENSE.txt
plonetheme/__init__.py
plonetheme.broadcaster.egg-info/PKG-INFO
plonetheme.broadcaster.egg-info/SOURCES.txt
plonetheme.broadcaster.egg-info/dependency_links.txt
plonetheme.broadcaster.egg-info/entry_points.txt
plonetheme.broadcaster.egg-info/namespace_packages.txt
plonetheme.broadcaster.egg-info/not-zip-safe
plonetheme.broadcaster.egg-info/paster_plugins.txt
plonetheme.broadcaster.egg-info/requires.txt
plonetheme.broadcaster.egg-info/top_level.txt
plonetheme/broadcaster/__init__.py
plonetheme/broadcaster/configure.zcml
plonetheme/broadcaster/profiles.zcml
plonetheme/broadcaster/setuphandlers.py
plonetheme/broadcaster/skins.zcml
plonetheme/broadcaster/tests.py
plonetheme/broadcaster/version.txt
plonetheme/broadcaster/browser/__init__.py
plonetheme/broadcaster/browser/configure.zcml
plonetheme/broadcaster/browser/credits.pt
plonetheme/broadcaster/browser/interfaces.py
plonetheme/broadcaster/browser/viewlet.pt
plonetheme/broadcaster/browser/viewlets.py
plonetheme/broadcaster/browser/images/README.txt
plonetheme/broadcaster/browser/stylesheets/README.txt
plonetheme/broadcaster/browser/stylesheets/main.css
plonetheme/broadcaster/profiles/default/cssregistry.xml
plonetheme/broadcaster/profiles/default/import_steps.xml
plonetheme/broadcaster/profiles/default/jsregistry.xml
plonetheme/broadcaster/profiles/default/metadata.xml
plonetheme/broadcaster/profiles/default/plonetheme.broadcaster_various.txt
plonetheme/broadcaster/profiles/default/skins.xml
plonetheme/broadcaster/profiles/default/viewlets.xml
plonetheme/broadcaster/skins/plonetheme_broadcaster_custom_images/CONTENT.txt
plonetheme/broadcaster/skins/plonetheme_broadcaster_custom_images/body-bg.png
plonetheme/broadcaster/skins/plonetheme_broadcaster_custom_images/code.png
plonetheme/broadcaster/skins/plonetheme_broadcaster_custom_images/ff.jpg
plonetheme/broadcaster/skins/plonetheme_broadcaster_custom_images/header.png
