Metadata-Version: 1.0
Name: plonetheme.broadcaster
Version: 1.0dev-r415
Summary: An installable theme for Plone 3.0
Home-page: http://www.themebin.com
Author: Themebin, ported to plone by Izhar Firdaus
Author-email: ''
License: Creative Commons 2.5
Keywords: web zope plone theme
Platform: UNKNOWN
Classifier: Framework :: Plone
Classifier: Programming Language :: Python
Classifier: Topic :: Software Development :: Libraries :: Python Modules
